saxo/NOTICE
saxo/README.md
saxo/__init__.py
saxo/common.py
saxo/core.py
saxo/create.py
saxo/daemon.py
saxo/irc.py
saxo/saxo.py
saxo/scheduler.py
saxo/script.py
saxo/sqlite.py
saxo/version
saxo/web.py
saxo/commands/at
saxo/commands/authorised
saxo/commands/bing
saxo/commands/bingc
saxo/commands/btc
saxo/commands/btr
saxo/commands/btr-key
saxo/commands/bytes
saxo/commands/c
saxo/commands/cap
saxo/commands/date
saxo/commands/dety
saxo/commands/dim
saxo/commands/distance
saxo/commands/dns
saxo/commands/duck
saxo/commands/ety
saxo/commands/g
saxo/commands/gc
saxo/commands/gcalc
saxo/commands/gcs
saxo/commands/gctor
saxo/commands/geo
saxo/commands/geoip
saxo/commands/get
saxo/commands/gim
saxo/commands/github-test
saxo/commands/gnews
saxo/commands/google
saxo/commands/gtor
saxo/commands/head
saxo/commands/img
saxo/commands/in
saxo/commands/ipa
saxo/commands/isgd
saxo/commands/isup
saxo/commands/join
saxo/commands/leave
saxo/commands/len
saxo/commands/leo
saxo/commands/location
saxo/commands/lpd
saxo/commands/ls
saxo/commands/news
saxo/commands/ng
saxo/commands/nokiageo
saxo/commands/npl
saxo/commands/off
saxo/commands/on
saxo/commands/part
saxo/commands/periodic
saxo/commands/pick
saxo/commands/pipe
saxo/commands/prefix
saxo/commands/private-channel
saxo/commands/public-channel
saxo/commands/punycode
saxo/commands/py
saxo/commands/quit
saxo/commands/r2r
saxo/commands/rdns
saxo/commands/reddit-random-test
saxo/commands/reload
saxo/commands/remove-unicode-data
saxo/commands/saxo
saxo/commands/seen
saxo/commands/sleep
saxo/commands/snippets
saxo/commands/source
saxo/commands/ssl
saxo/commands/suggest
saxo/commands/t
saxo/commands/time
saxo/commands/title
saxo/commands/to
saxo/commands/tr
saxo/commands/tw
saxo/commands/tweet
saxo/commands/twop
saxo/commands/tzinfo
saxo/commands/u
saxo/commands/ud
saxo/commands/unicode-by-character
saxo/commands/unicode-by-codepoint
saxo-0.3.4.dist-info/DESCRIPTION.rst
saxo-0.3.4.dist-info/METADATA
saxo-0.3.4.dist-info/RECORD
saxo-0.3.4.dist-info/WHEEL
saxo-0.3.4.dist-info/metadata.json
saxo-0.3.4.dist-info/top_level.txt
