Metadata-Version: 2.0
Name: saxo
Version: 0.3.4
Summary: Quick and flexible irc bot, extensible in any language
Home-page: http://inamidst.com/saxo/
Author: Sean B. Palmer
Author-email: UNKNOWN
License: Apache License 2.0
Platform: Linux and OS X
Classifier: Operating System :: MacOS :: MacOS X
Classifier: Operating System :: POSIX
Classifier: Programming Language :: Python :: 3
